{
  "name": "Amelia Bass",
  "age": 22,
  "address": {
    "street": "Ipuelu Way",
    "city": "Fuduzev",
    "state": "IL",
    "zip": "63458"
  },
  "contact": {
    "phone": "(867) 742-5132",
    "servicePhone": "800476572"
  },
  "birthday": "1980-07-04T14:36:24.114Z",
  "ip": "126.237.213.153",
  "foo": "bar",
  "profile": {
    "about": "An emukazel ugun burje acugiwfam sunvuh awejoedi tojejkec vafu alevum nonzejvik asiwu voga urrus ma diosowo. Gelerfe faijace lupu su bav diemo figep faf pefipezar numewva jumpimaz ukuho com urzapus. Fiju ih hepneuk pi dofner ahijifo we vu ubili zu hi urfobe me dag naliwke canu etivusig bez. Loka lupuba wepocna eco siklan babzompir widecis oweoham zut geg zikpaaro mivamu. Et ken alabicmi peseka bo egheizu sor rarwol ava apibi vodete nanwed hajo. Lulba gub wef ra apajek higmek wemzehhi hamo muugu ovi gumonco defva tot ram. Ugtabub us pid oce lelwires gap zus neral dagtodu maseh masut tohricnul.",
    "bio": "Nem rasbolson gi uno puabpor suvujfog pagaper keveb gezdira hi ropulna dusi dutba zasor. Taj vetables mihuv ekfi iloeka ipolo sugu fi mid lajhel livsu sefora ezujap obtusbiv butkoc go. Num vunilu siso medjadbu tuz wetcechok bapgeuh si pujigu janu jufod zauma ceajbe dodzo. Cilamuvis mo lut delulek fos nap jeonwe zizi dimuhab vab go onazof. Miruknir tezkud elvu lodooko deopa zodetik jigednus ut op ruomusaw dav cembi derouv huilu gir."
  },
  "apiKey": "6c31ae4851c18d84f7b7563feb4f8c97320c9030bd040230ebe00751bf549ab2",
  "currency": {
    "code": "AUD",
    "name": "Australia Dollar"
  }
}