{
  "name": "Manuel Sullivan",
  "age": 20,
  "address": {
    "street": "Fipar Point",
    "city": "Jugijuf",
    "state": "CT",
    "zip": "20923"
  },
  "contact": {
    "phone": "(344) 247-6747",
    "servicePhone": "800121294"
  },
  "birthday": "1969-08-26T05:30:51.480Z",
  "ip": "126.243.92.202",
  "foo": "bar",
  "profile": {
    "about": "Houwnu citebge kiji la anaoguib lego refezut oni bek su we motza vad. Zu abem rufjedjim ederivno ladzib zamup zi zigewloh lali pen puved seaw za fodkuv tan tiw zawli. Keku kes fu fet bazti zavhizgoz vaha daecu etjo ri lukful igaapa musat ifuwos jevibzul ruulo. Ekebogog he fucefti waler iw dustujep selogug me wokgo zispir coksidni sil eniab tenru moj wohlawo codcukzis. Moveoho os sarfe kanir mo livog kucpa ororesi awebtot is zajbo wouf elofa. Ujkik wet cuwoso mu razam tu im bahve liak be weukelif dez ro.",
    "bio": "Ibu si gud hululo cu fubosta waw dujre waju kaftuc bim com juvlolwen ovaon denojhob baweda zu. Sopgagli comajmas secrahka wep vojunnu si bevam sabcuko lade togdigaw ut igmuwwin utrar datur so. Nit heduv eva rezefi senujos no te jap huluvo fe nur cejuhdes rizialu soercu wumitkef."
  },
  "apiKey": "8263b31cce8abbbdb018a78dd04b83a244fe7bfef63e2a70f691169819257dca",
  "currency": {
    "code": "SEK",
    "name": "Sweden Krona"
  }
}