{
  "name": "Olive Ortega",
  "age": 28,
  "address": {
    "street": "Vepas Pass",
    "city": "Vurodec",
    "state": "HI",
    "zip": "46019"
  },
  "contact": {
    "phone": "(202) 409-1569",
    "servicePhone": "800561541"
  },
  "birthday": "1985-05-23T07:49:51.238Z",
  "ip": "179.225.95.191",
  "foo": "bar",
  "profile": {
    "about": "Ko defub mu huziog mi pagan otoha larel udo sow kudhi wiheb lo ve tozjid ni kofjofaz. Ja tawama febdazep hatra jupeffeb pa niglib wab mibdokte voltaczo ro tijiwsi. Emimos sed hesja zez ziv hitbizu wagaz gasel retawso paapuje jimmavo dehorivit ragorufo.",
    "bio": "Ibozenfu kik kalneup wa upitwu zecpen kamu afivofbin pejetu tep ca mupce. Sutvu walvig jon oje at ufituc rineb rod vizno aknuw asapiju lojkoici ne di. Jiwmisro uddisbu rownoz im awiguvu gedmen veiv iskune agzaro ep saen wofieb misi ju rozga renecfi."
  },
  "apiKey": "10122e7c4bcfa273d6d4f9b2e689825d256beed361f258d8508129f5e3347921",
  "currency": {
    "code": "ANG",
    "name": "Netherlands Antilles Guilder"
  }
}